README.md
setup.py
proxyport/__init__.py
proxyport/__main__.py
proxyport/__version__.py
proxyport/proxyport.py
proxyport.egg-info/PKG-INFO
proxyport.egg-info/SOURCES.txt
proxyport.egg-info/dependency_links.txt
proxyport.egg-info/top_level.txt