Metadata-Version: 2.1
Name: proxyport
Version: 1.0.0
Summary: Proxy Port SDK package.
Home-page: https://github.com/proxyport/py-proxyport
Author: Proxy Port
Author-email: proxyportcom@gmail.com
License: MIT
Platform: UNKNOWN
Classifier: License :: OSI Approved :: MIT License
Classifier: Programming Language :: Python
Classifier: Programming Language :: Python :: 3
Classifier: Programming Language :: Python :: 3.6
Classifier: Programming Language :: Python :: Implementation :: CPython
Classifier: Programming Language :: Python :: Implementation :: PyPy
Requires-Python: >=3.6.0
